Classfile /E:/JAVA-01/Week_01/2021-02-28/week1/src/main/java/com/xianyanyang/jvm/bytecode/StaticMethod.class
  Last modified 2021-3-2; size 396 bytes
  MD5 checksum cd592666b36421c15c59ab0ce5c8415c
  Compiled from "StaticMethod.java"
public class com.xianyanyang.jvm.bytecode.StaticMethod
  minor version: 0
  major version: 52
  flags: ACC_PUBLIC, ACC_SUPER
Constant pool:
   #1 = Methodref          #3.#16         // java/lang/Object."<init>":()V
   #2 = Class              #17            // com/xianyanyang/jvm/bytecode/StaticMethod
   #3 = Class              #18            // java/lang/Object
   #4 = Utf8               <init>
   #5 = Utf8               ()V
   #6 = Utf8               Code
   #7 = Utf8               LineNumberTable
   #8 = Utf8               LocalVariableTable
   #9 = Utf8               this
  #10 = Utf8               Lcom/xianyanyang/jvm/bytecode/StaticMethod;
  #11 = Utf8               foo
  #12 = Utf8               i
  #13 = Utf8               I
  #14 = Utf8               SourceFile
  #15 = Utf8               StaticMethod.java
  #16 = NameAndType        #4:#5          // "<init>":()V
  #17 = Utf8               com/xianyanyang/jvm/bytecode/StaticMethod
  #18 = Utf8               java/lang/Object
{
  public com.xianyanyang.jvm.bytecode.StaticMethod();
    descriptor: ()V
    flags: ACC_PUBLIC
    Code:
      stack=1, locals=1, args_size=1
         0: aload_0
         1: invokespecial #1                  // Method java/lang/Object."<init>":()V
         4: return
      LineNumberTable:
        line 3: 0
      LocalVariableTable:
        Start  Length  Slot  Name   Signature
            0       5     0  this   Lcom/xianyanyang/jvm/bytecode/StaticMethod;

  public static void foo();
    descriptor: ()V
    flags: ACC_PUBLIC, ACC_STATIC
    Code:
      stack=1, locals=1, args_size=0
         0: iconst_0
         1: istore_0
         2: return
      LineNumberTable:
        line 6: 0
        line 7: 2
      LocalVariableTable:
        Start  Length  Slot  Name   Signature
            2       1     0     i   I
}
SourceFile: "StaticMethod.java"
